main.py
utils/__init__.py
utils/cache.py
utils/constants.py
utils/display.py
utils/mcp.py
utils/models.py
utils/paste.py
microcode-0.2.3.dist-info/METADATA
microcode-0.2.3.dist-info/WHEEL
microcode-0.2.3.dist-info/entry_points.txt
microcode-0.2.3.dist-info/top_level.txt
microcode-0.2.3.dist-info/RECORD
