Metadata-Version: 2.4
Name: microcode
Version: 0.2.3
Summary: Minimal Terminal Agent powered by RLMs
Author-email: Farouk Adeleke <farouk@modaic.dev>
Project-URL: Homepage, https://modaic.dev/
Project-URL: Repository, https://github.com/modaic-ai/microcode
Project-URL: Issues, https://github.com/modaic-ai/microcode/issues
Classifier: Development Status :: 3 - Alpha
Classifier: Environment :: Console
Classifier: Intended Audience :: Developers
Classifier: License :: OSI Approved :: MIT License
Classifier: Programming Language :: Python :: 3
Classifier: Programming Language :: Python :: 3 :: Only
Classifier: Programming Language :: Python :: 3.11
Classifier: Topic :: Software Development :: Build Tools
Classifier: Topic :: Utilities
Requires-Python: >=3.11
Requires-Dist: click>=8.3.1
Requires-Dist: dspy>=3.1.2
Requires-Dist: mcp2py>=0.6.0
Requires-Dist: modaic>=0.10.4
Requires-Dist: prompt-toolkit>=3.0.52
Requires-Dist: rich>=14.2.0
Requires-Dist: textual>=7.3.0
Requires-Dist: typer>=0.21.1
Requires-Dist: weave>=0.52.25
